{
"type": "FeatureCollection",
"name": "Priority_Improvements",
"crs": { "type": "name", "properties": { "name": "urn:ogc:def:crs:OGC:1.3:CRS84" } },
"features": [
{ "type": "Feature", "properties": { "Name": "Taghum Bridge", "Description": "The Taghum Footbridge Society is currently working on a crowdfunding campaign to build an active transportation link accross the Kootenay River. For more information and donation platform, please visit: https://taghumbridge.org/", "Priority": "High", "URL": "http://taghumbridge.org", "Comment": null }, "geometry": { "type": "Point", "coordinates": [ -117.389546536660418, 49.487555493262327 ] } },
{ "type": "Feature", "properties": { "Name": "Slocan Rail - Hwy 6 Crossing", "Description": "Need for New Safe Hwy Crossing", "Priority": "High", "URL": null, "Comment": "MOT" }, "geometry": { "type": "Point", "coordinates": [ -117.559438618010233, 49.451154452948678 ] } },
{ "type": "Feature", "properties": { "Name": "Delbruck to Great Northern Trail", "Description": "Construction of More Accessable Access", "Priority": "High", "URL": null, "Comment": "2026" }, "geometry": { "type": "Point", "coordinates": [ -117.28197, 49.483313 ] } },
{ "type": "Feature", "properties": { "Name": "Nelson North Shore Shoulder Improvements", "Description": "The WKCC is working with the RDCK, MOTI, and YRB to make improvements to the Nelson North Shore section of Highway 3A from Nelson to Balfour.", "Priority": "High", "URL": null, "Comment": "Ongoing as work occurs" }, "geometry": { "type": "Point", "coordinates": [ -117.276591569701267, 49.523425765714265 ] } }
]
}
